new_hd_tools/__init__.py
new_hd_tools/crypto.py
new_hd_tools/hd_tools.py
new_hd_tools-0.1.0.dist-info/DESCRIPTION.rst
new_hd_tools-0.1.0.dist-info/METADATA
new_hd_tools-0.1.0.dist-info/RECORD
new_hd_tools-0.1.0.dist-info/WHEEL
new_hd_tools-0.1.0.dist-info/metadata.json
new_hd_tools-0.1.0.dist-info/top_level.txt
